setup.py
GENERAL7/__init__.py
GENERAL7.egg-info/PKG-INFO
GENERAL7.egg-info/SOURCES.txt
GENERAL7.egg-info/dependency_links.txt
GENERAL7.egg-info/top_level.txt