Metadata-Version: 2.4
Name: GENERAL7
Version: 3.1.0
Summary: This library is from my programming For Accounts,Users..GENERAL_Iraq_@GN_R7
Author: GENERAL:@GN_R7
Classifier: Programming Language :: Python :: 3
Classifier: Operating System :: OS Independent
Classifier: License :: OSI Approved :: MIT License
Dynamic: author
Dynamic: classifier
Dynamic: summary
